shaphypetune/__init__.py
shaphypetune/_classes.py
shaphypetune/shaphypetune.py
shaphypetune/utils.py
shap_hypetune-0.2.7.dist-info/LICENSE
shap_hypetune-0.2.7.dist-info/METADATA
shap_hypetune-0.2.7.dist-info/WHEEL
shap_hypetune-0.2.7.dist-info/top_level.txt
shap_hypetune-0.2.7.dist-info/RECORD
