Metadata-Version: 2.1
Name: shap-hypetune
Version: 0.2.7
Summary: A python package for simultaneous Hyperparameters Tuning and Features Selection for Gradient Boosting Models.
Home-page: https://github.com/cerlymarco/shap-hypetune
Author: Marco Cerliani
Author-email: cerlymarco@gmail.com
License: MIT
Requires-Python: >=3
License-File: LICENSE
Requires-Dist: numpy
Requires-Dist: scipy
Requires-Dist: scikit-learn (>=0.24.1)
Requires-Dist: shap (>=0.39.0)
Requires-Dist: hyperopt (==0.2.5)
